odoo/addons/ssi_voucher_mixin/README.rst
odoo/addons/ssi_voucher_mixin/__init__.py
odoo/addons/ssi_voucher_mixin/__manifest__.py
odoo/addons/ssi_voucher_mixin/menu.xml
odoo/addons/ssi_voucher_mixin/i18n/ssi_voucher_mixin.pot
odoo/addons/ssi_voucher_mixin/models/__init__.py
odoo/addons/ssi_voucher_mixin/models/account_journal.py
odoo/addons/ssi_voucher_mixin/models/voucher_line_mixin.py
odoo/addons/ssi_voucher_mixin/models/voucher_line_summary_mixin.py
odoo/addons/ssi_voucher_mixin/models/voucher_line_tax_mixin.py
odoo/addons/ssi_voucher_mixin/models/voucher_mixin.py
odoo/addons/ssi_voucher_mixin/models/voucher_type.py
odoo/addons/ssi_voucher_mixin/models/voucher_type_allowed_journal.py
odoo/addons/ssi_voucher_mixin/security/ir.model.access.csv
odoo/addons/ssi_voucher_mixin/static/description/banner.png
odoo/addons/ssi_voucher_mixin/static/description/icon.png
odoo/addons/ssi_voucher_mixin/views/account_voucher_type_allowed_journal_views.xml
odoo/addons/ssi_voucher_mixin/views/account_voucher_type_views.xml
odoo/addons/ssi_voucher_mixin/views/mixin_account_voucher_views.xml
odoo/addons/ssi_voucher_mixin/wizards/__init__.py
odoo/addons/ssi_voucher_mixin/wizards/wizard_add_journal_to_voucher_type.py
odoo/addons/ssi_voucher_mixin/wizards/wizard_add_journal_to_voucher_type.xml
odoo/addons/ssi_voucher_mixin/wizards/wizard_import_move_line.py
odoo/addons/ssi_voucher_mixin/wizards/wizard_import_move_line.xml
odoo/addons/ssi_voucher_mixin/wizards/wizard_post_voucher.py
odoo/addons/ssi_voucher_mixin/wizards/wizard_post_voucher.xml
odoo14_addon_ssi_voucher_mixin-14.0.2.2.0.dist-info/METADATA
odoo14_addon_ssi_voucher_mixin-14.0.2.2.0.dist-info/WHEEL
odoo14_addon_ssi_voucher_mixin-14.0.2.2.0.dist-info/top_level.txt
odoo14_addon_ssi_voucher_mixin-14.0.2.2.0.dist-info/RECORD
